<?xml version="1.0" encoding="UTF-8"?>
<dataroot>
    <title>
        <tit>فاتحة الكتاب</tit>
        <id>4</id>
        <lvl>1</lvl>
    </title>
    <title>
        <tit>خطة الكتاب</tit>
        <id>8</id>
        <lvl>1</lvl>
    </title>
    <title>
        <tit>القسم الأول من الكتاب مقدمات عامة</tit>
        <id>11</id>
        <lvl>1</lvl>
    </title>
    <title>
        <tit>الباب الأول تعريف بمناخ نشأة المذاهب الفكرية المعاصرة</tit>
        <id>12</id>
        <lvl>2</lvl>
    </title>
    <title>
        <tit>مقدمة عامة</tit>
        <id>13</id>
        <lvl>3</lvl>
    </title>
    <title>
        <tit>الفصل الأول مناخ نشأة المذاهب الفكرية المعاصرة في أوربا</tit>
        <id>15</id>
        <lvl>4</lvl>
    </title>
    <title>
        <tit>الفصل الثاني تحرك اليهود مستغلين المناخ الملائم في أوربا</tit>
        <id>50</id>
        <lvl>4</lvl>
    </title>
    <title>
        <tit>الفصل الثالث: أسباب تقبل شعوب الأمة الإسلامية لوافدات المذاهب الفكرية المعاصرة</tit>
        <id>81</id>
        <lvl>4</lvl>
    </title>
    <title>
        <tit>الباب الثاني وسائل التضليل لترويج الشعارات والآراء والمذاهب الفكرية المزيفة</tit>
        <id>91</id>
        <lvl>2</lvl>
    </title>
    <title>
        <tit>الفصل الأول الخطة العامة</tit>
        <id>92</id>
        <lvl>3</lvl>
    </title>
    <title>
        <tit>الفصل الثاني المغالطات الجدلية</tit>
        <id>112</id>
        <lvl>3</lvl>
    </title>
    <title>
        <tit>الفصل الثالث لعبة تطبيق المنهج العلمي الخاص بالجبريات على السلوك الإرادي عند الإنسان</tit>
        <id>134</id>
        <lvl>3</lvl>
    </title>
    <title>
        <tit>القسم الثاني من الكتاب عرض لأهم الشعارات البراقة المزيفة ولآراء ومذاهب فكرية معاصرة جزئية منبثقة في علوم مختلفة مع كشف زيوفها وتعريف بأئمتها</tit>
        <id>143</id>
        <lvl>1</lvl>
    </title>
    <title>
        <tit>الباب الأول مقدمات حول اعتماد العقل والعلم الإنساني بديلا للدين</tit>
        <id>144</id>
        <lvl>2</lvl>
    </title>
    <title>
        <tit>الفصل الأول العقلانية</tit>
        <id>145</id>
        <lvl>3</lvl>
    </title>
    <title>
        <tit>الفصل الثاني العلمانية</tit>
        <id>147</id>
        <lvl>3</lvl>
    </title>
    <title>
        <tit>الباب الثاني افتراءات تروج ضد الدين والأخلاق والقوانين والنظم المنبثقة عنهما</tit>
        <id>155</id>
        <lvl>2</lvl>
    </title>
    <title>
        <tit>الفصل الأول فرية التناقض بين العقل والدين وبين العلم والدين</tit>
        <id>156</id>
        <lvl>3</lvl>
    </title>
    <title>
        <tit>الفصل الثاني مزاعم المضلين لهدم أسس الأخلاق وأبنيتها وتطبيقاتها في المجتمع</tit>
        <id>184</id>
        <lvl>3</lvl>
    </title>
    <title>
        <tit>الباب الثالث خداع الشعارات التي يتولد عنها في الرأي العام مسلمات خاطئات وموقف الإسلام من كل منها</tit>
        <id>200</id>
        <lvl>2</lvl>
    </title>
    <title>
        <tit>المقدمة</tit>
        <id>201</id>
        <lvl>3</lvl>
    </title>
    <title>
        <tit>الفصل الأول الحرية</tit>
        <id>204</id>
        <lvl>3</lvl>
    </title>
    <title>
        <tit>الفصل الثاني المساواة</tit>
        <id>212</id>
        <lvl>3</lvl>
    </title>
    <title>
        <tit>الفصل الثالث التقدمية والرجعية</tit>
        <id>220</id>
        <lvl>3</lvl>
    </title>
    <title>
        <tit>الفصل الرابع الاشتراكية</tit>
        <id>225</id>
        <lvl>3</lvl>
    </title>
    <title>
        <tit>الفصل الخامس الوطنية والقومية والإنسانية وموقف الإسلام من كل منها</tit>
        <id>227</id>
        <lvl>3</lvl>
    </title>
    <title>
        <tit>الباب الرابع أئمة ومذاهب جزئية في علوم مختلفة</tit>
        <id>266</id>
        <lvl>2</lvl>
    </title>
    <title>
        <tit>الفصل الأول فرويد ومدرسته في علم النفس</tit>
        <id>267</id>
        <lvl>3</lvl>
    </title>
    <title>
        <tit>الفصل الثاني داروين ومذهب التطور</tit>
        <id>293</id>
        <lvl>3</lvl>
    </title>
    <title>
        <tit>الفصل الثالث دوركايم وآراؤه في علم الاجتماع</tit>
        <id>311</id>
        <lvl>3</lvl>
    </title>
    <title>
        <tit>الفصل الرابع برجسون وآراؤه في نشأة الدين والأخلاق</tit>
        <id>325</id>
        <lvl>3</lvl>
    </title>
    <title>
        <tit>الفصل الخامس سارتر وآراؤه الفلسفية في الوجودية</tit>
        <id>335</id>
        <lvl>3</lvl>
    </title>
    <title>
        <tit>الفصل السادس مكيافيلي وفكرة: الغاية تبرر الوسيلة</tit>
        <id>355</id>
        <lvl>3</lvl>
    </title>
    <title>
        <tit>الفصل السابع ماركوز وآراؤه الثورية لإقامة ديكتاتورية حكم الأقلية الواعية</tit>
        <id>369</id>
        <lvl>3</lvl>
    </title>
    <title>
        <tit>الفصل الثامن أوجست كونت ودين الإنسانية</tit>
        <id>381</id>
        <lvl>3</lvl>
    </title>
    <title>
        <tit>القسم الثالث من الكتاب أئمة ومذاهب فكرية معاصرة كبيرة</tit>
        <id>404</id>
        <lvl>1</lvl>
    </title>
    <title>
        <tit>الباب الأول المادية الإلحادية والماديون</tit>
        <id>405</id>
        <lvl>2</lvl>
    </title>
    <title>
        <tit>الفصل الأول مقدمات عامة</tit>
        <id>406</id>
        <lvl>3</lvl>
    </title>
    <title>
        <tit>الفصل الثاني أئمة ماديون ونبذ من آرائهم الفلسفية الإلحادية</tit>
        <id>416</id>
        <lvl>3</lvl>
    </title>
    <title>
        <tit>الفصل الثالث أسس الفكر المادي الإلحادي</tit>
        <id>479</id>
        <lvl>3</lvl>
    </title>
    <title>
        <tit>الفصل الرابع كشف زيوف أفكار الماديين وجدليتهم</tit>
        <id>492</id>
        <lvl>3</lvl>
    </title>
    <title>
        <tit>الفصل الخامس عقوبة العذاب النفسي للملحدين</tit>
        <id>524</id>
        <lvl>3</lvl>
    </title>
    <title>
        <tit>الفصل السادس المادية الجدلية في الكون والتاريخ الإنساني</tit>
        <id>532</id>
        <lvl>3</lvl>
    </title>
    <title>
        <tit>الباب الثاني النظم الاقتصادية المعاصرة</tit>
        <id>560</id>
        <lvl>2</lvl>
    </title>
    <title>
        <tit>الفصل الأول نظرة تاريخية حول المذاهب الوضعية للنظم الاقتصادية</tit>
        <id>561</id>
        <lvl>3</lvl>
    </title>
    <title>
        <tit>الفصل الثاني لمحة موجزة حول منهج دين الله</tit>
        <id>571</id>
        <lvl>3</lvl>
    </title>
    <title>
        <tit>الفصل الثالث مقارنة بين المذاهب الاقتصادية</tit>
        <id>592</id>
        <lvl>3</lvl>
    </title>
    <title>
        <tit>الفصل الرابع نظرات متفرقة</tit>
        <id>624</id>
        <lvl>3</lvl>
    </title>
    <title>
        <tit>الباب الثالث النظم السياسية المعاصرة</tit>
        <id>638</id>
        <lvl>2</lvl>
    </title>
    <title>
        <tit>الفصل الأول نظرة تاريخية حول المذاهب الوضعية للنظم السياسية</tit>
        <id>639</id>
        <lvl>3</lvl>
    </title>
    <title>
        <tit>الفصل الثاني لمحة موجزة حول منهج دين الله للناس في شؤون الحكم</tit>
        <id>647</id>
        <lvl>3</lvl>
    </title>
    <title>
        <tit>الفصل الثالث مقارنة بين النظم السياسية</tit>
        <id>676</id>
        <lvl>3</lvl>
    </title>
    <title>
        <tit>الفصل الرابع متفرقات</tit>
        <id>700</id>
        <lvl>3</lvl>
    </title>
</dataroot>
