<?xml version="1.0" encoding="UTF-8"?>
<dataroot>
    <title>
        <tit>باب آداب المشي إلى الصلاة</tit>
        <id>1</id>
        <lvl>1</lvl>
    </title>
    <title>
        <tit>باب صفة الصلاة</tit>
        <id>4</id>
        <lvl>1</lvl>
    </title>
    <title>
        <tit>جهر الإمام بالتكبير</tit>
        <id>6</id>
        <lvl>2</lvl>
    </title>
    <title>
        <tit>الصلاة في مكان شديد الحر أو شديد البرد</tit>
        <id>16</id>
        <lvl>2</lvl>
    </title>
    <title>
        <tit>الذكر والدعاء والاستغفار عقب الصلاة</tit>
        <id>24</id>
        <lvl>2</lvl>
    </title>
    <title>
        <tit>الصلاة إلى سترة</tit>
        <id>29</id>
        <lvl>2</lvl>
    </title>
    <title>
        <tit>الواجبات التي تسقط سهوا</tit>
        <id>33</id>
        <lvl>2</lvl>
    </title>
    <title>
        <tit>سجود السهو</tit>
        <id>36</id>
        <lvl>2</lvl>
    </title>
    <title>
        <tit>العمل اليسير في الصلاة</tit>
        <id>38</id>
        <lvl>2</lvl>
    </title>
    <title>
        <tit>من شك في عدد الركعات</tit>
        <id>39</id>
        <lvl>2</lvl>
    </title>
    <title>
        <tit>باب صلاة التطوع</tit>
        <id>41</id>
        <lvl>1</lvl>
    </title>
</dataroot>
